AUTHORS
CHANGELOG.md
CONTRIBUTING.md
Dockerfile
LICENSE
MAINTAINERS
MANIFEST.in
Makefile
README.md
setup.py
api/Dockerfile
api/index.html
api/swagger-ui.js
bin/vcontrol
docs/README.md
docs/TEST.md
vcontrol/__init__.py
vcontrol/requirements.txt
vcontrol/swagger.yaml
vcontrol/vcontrol.py
vcontrol/vmware-stats
vcontrol.egg-info/PKG-INFO
vcontrol.egg-info/SOURCES.txt
vcontrol.egg-info/dependency_links.txt
vcontrol.egg-info/requires.txt
vcontrol.egg-info/top_level.txt
vcontrol/cli/__init__.py
vcontrol/cli/version.py
vcontrol/cli/commands/__init__.py
vcontrol/cli/commands/build.py
vcontrol/cli/commands/clean.py
vcontrol/cli/commands/deploy.py
vcontrol/cli/commands/download.py
vcontrol/cli/commands/generic.py
vcontrol/cli/commands/info.py
vcontrol/cli/commands/logs.py
vcontrol/cli/commands/mimetypes.py
vcontrol/cli/commands/start.py
vcontrol/cli/commands/stats.py
vcontrol/cli/commands/status.py
vcontrol/cli/commands/stop.py
vcontrol/cli/commands/upload.py
vcontrol/cli/commands/plugins/__init__.py
vcontrol/cli/commands/plugins/add.py
vcontrol/cli/commands/plugins/list_all.py
vcontrol/cli/commands/plugins/remove.py
vcontrol/cli/commands/plugins/update.py
vcontrol/cli/machines/__init__.py
vcontrol/cli/machines/boot.py
vcontrol/cli/machines/create.py
vcontrol/cli/machines/delete.py
vcontrol/cli/machines/heartbeat.py
vcontrol/cli/machines/list_all.py
vcontrol/cli/machines/reboot.py
vcontrol/cli/machines/register.py
vcontrol/cli/machines/shutdown.py
vcontrol/cli/machines/ssh.py
vcontrol/cli/machines/unregister.py
vcontrol/cli/providers/__init__.py
vcontrol/cli/providers/add.py
vcontrol/cli/providers/heartbeat.py
vcontrol/cli/providers/info.py
vcontrol/cli/providers/list_all.py
vcontrol/cli/providers/remove.py
vcontrol/cli/providers/stats.py
vcontrol/rest/__init__.py
vcontrol/rest/index.py
vcontrol/rest/swagger.py
vcontrol/rest/version.py
vcontrol/rest/commands/__init__.py
vcontrol/rest/commands/build.py
vcontrol/rest/commands/clean.py
vcontrol/rest/commands/deploy.py
vcontrol/rest/commands/download.py
vcontrol/rest/commands/generic.py
vcontrol/rest/commands/info.py
vcontrol/rest/commands/logs.py
vcontrol/rest/commands/mimetypes.py
