Metadata-Version: 1.1
Name: vcontrol
Version: 0.3.1
Summary: Vent control layer for managing Vent instances
Home-page: https://github.com/CyberReboot/vcontrol
Author: Charlie Lewis
Author-email: clewis@iqt.org
License: LICENSE
Platform: UNKNOWN
Classifier: Programming Language :: Python
Classifier: Operating System :: POSIX :: Linux
Classifier: Topic :: Software Development :: Libraries :: Application Frameworks
Classifier: Environment :: Other Environment
